pytriage/__init__.py
pytriage/pytriage.py
PyTriage-0.1.0.dist-info/LICENSE
PyTriage-0.1.0.dist-info/METADATA
PyTriage-0.1.0.dist-info/WHEEL
PyTriage-0.1.0.dist-info/top_level.txt
PyTriage-0.1.0.dist-info/RECORD
