Metadata-Version: 2.1
Name: PyTriage
Version: 0.1.0
Summary: PyTriage is a Python library for interacting with Cofense Triage's v2 API.
Home-page: https://github.com/tyler-tee/pytriage
Author: Tyler Talaga
Author-email: ttalaga@wgu.edu
License: GPLv3
Platform: UNKNOWN
